Sfigures/__init__.py
Sfigures/figures.py
Sfigures/utils.py
sfigures_sen-0.1.6.dist-info/METADATA
sfigures_sen-0.1.6.dist-info/WHEEL
sfigures_sen-0.1.6.dist-info/top_level.txt
sfigures_sen-0.1.6.dist-info/RECORD
