Metadata-Version: 2.4
Name: SFigures-sen
Version: 0.1.6
Summary: Простая библиотека для расчета площадей фигур
Author-email: Sen <apelsinkap3@gmail.com>
Classifier: Programming Language :: Python :: 3
Classifier: License :: OSI Approved :: MIT License
Classifier: Operating System :: OS Independent
Requires-Python: >=3.7
